Workbook

Sheet 全局参数
A1: 全局参数 —— 标准玩家画像（零充 / 轻微付费）：收支模型的唯一参数源
A3: 模拟天数 | B3: 90 | C3: 生态模拟周期
A4: 天空石日收入 | B4: 195 | C4: 日常任务100 + 成就50 + 周任务摊销45
A5: 十连抽成本（天空石） | B5: 9500 | C5: 950 × 10；玩家每 30 天执行一次十连
A6: 十连周期（天） | B6: 30 | C6: MOD(天数,周期)=0 时执行十连
A7: 天空石其他支出（日均） | B7: 22 | C7: 商店刷新 / 体力购买折算
A8: 金币日收入 | B8: 400000 | C8: 副本 / 出售装备 / 任务
A9: 金币日支出（养成摊销） | B9: 70000 | C9: 强化+升星+觉醒金币按 90 天养成计划摊销
A10: 金币日支出（商店杂项） | B10: 20000 | C10: 限时商店 / 猫窝购买
A11: 体力日收入 | B11: 900 | C11: 自然恢复720 + 日常领取180
A12: 体力日支出 | B12: 850 | C12: 刷图消耗——紧平衡设计：体力是日活闸门
A13: 荣誉日收入 | B13: 300 | C13: 竞技场结算 + 每日场次
A14: 荣誉日支出 | B14: 250 | C14: 荣誉商店兑换

Sheet 货币一览表
A1: 货币一览表（四类货币四种控速逻辑：天空石克制 / 金币通胀待回收 / 体力紧平衡 / 专用币定向）
A3: 货币 | B3: 类型 | C3: 主要获取 | D3: 主要消耗
A4: 天空石 | B4: 硬通货 | C4: 日常任务 / 成就 / 周任务 / 活动 | D4: 召唤（950/次） / 体力购买 / 商店刷新
A5: 金币 | B5: 软通货 | C5: 副本 / 出售装备 / 任务 / 活动 | D5: 装备强化 / 升星 / 觉醒符文 / 商店
A6: 体力 | B6: 行动力 | C6: 自然恢复 / 每日领取 / 天空石购买 | D6: 刷图（企鹅 / 符文 / 催化剂来源）
A7: 荣誉 | B7: 专用币 | C7: 竞技场场次与结算 | D7: 荣誉商店（装备 / 催化剂）
A8: 联盟币 | B8: 专用币 | C8: 联盟商战 / 捐献 | D8: 联盟商店

Sheet 90天收支模拟
A1: 90 天收支模拟（标准玩家：日收入恒定 + 周期性大额支出，余额公式逐日累计）
A3: 天数 | B3: 天空石收入 | C3: 天空石支出 | D3: 天空石余额 | E3: 金币收入 | F3: 金币支出 | G3: 金币余额 | H3: 体力余额 | I3: 荣誉余额
A4: 1 | B4: ='全局参数'!$B$4 | C4: =IF(MOD(A4,'全局参数'!$B$6)=0,'全局参数'!$B$5,0)+'全局参数'!$B$7 | D4: ='全局参数'!$B$4-(IF(MOD(A4,'全局参数'!$B$6)=0,'全局参数'!$B$5,0)+'全局参数'!$B$7) | E4: ='全局参数'!$B$8 | F4: ='全局参数'!$B$9+'全局参数'!$B$10 | G4: ='全局参数'!$B$8-('全局参数'!$B$9+'全局参数'!$B$10) | H4: ='全局参数'!$B$11-'全局参数'!$B$12 | I4: ='全局参数'!$B$13-'全局参数'!$B$14
A5: 2 | B5: ='全局参数'!$B$4 | C5: =IF(MOD(A5,'全局参数'!$B$6)=0,'全局参数'!$B$5,0)+'全局参数'!$B$7 | D5: =D4+B5-C5 | E5: ='全局参数'!$B$8 | F5: ='全局参数'!$B$9+'全局参数'!$B$10 | G5: =G4+E5-F5 | H5: H4+('全局参数'!$B$11-'全局参数'!$B$12) | I5: I4+('全局参数'!$B$13-'全局参数'!$B$14)
A6: 3 | B6: ='全局参数'!$B$4 | C6: =IF(MOD(A6,'全局参数'!$B$6)=0,'全局参数'!$B$5,0)+'全局参数'!$B$7 | D6: =D5+B6-C6 | E6: ='全局参数'!$B$8 | F6: ='全局参数'!$B$9+'全局参数'!$B$10 | G6: =G5+E6-F6 | H6: H5+('全局参数'!$B$11-'全局参数'!$B$12) | I6: I5+('全局参数'!$B$13-'全局参数'!$B$14)
A7: 4 | B7: ='全局参数'!$B$4 | C7: =IF(MOD(A7,'全局参数'!$B$6)=0,'全局参数'!$B$5,0)+'全局参数'!$B$7 | D7: =D6+B7-C7 | E7: ='全局参数'!$B$8 | F7: ='全局参数'!$B$9+'全局参数'!$B$10 | G7: =G6+E7-F7 | H7: H6+('全局参数'!$B$11-'全局参数'!$B$12) | I7: I6+('全局参数'!$B$13-'全局参数'!$B$14)
A8: 5 | B8: ='全局参数'!$B$4 | C8: =IF(MOD(A8,'全局参数'!$B$6)=0,'全局参数'!$B$5,0)+'全局参数'!$B$7 | D8: =D7+B8-C8 | E8: ='全局参数'!$B$8 | F8: ='全局参数'!$B$9+'全局参数'!$B$10 | G8: =G7+E8-F8 | H8: H7+('全局参数'!$B$11-'全局参数'!$B$12) | I8: I7+('全局参数'!$B$13-'全局参数'!$B$14)
A9: 6 | B9: ='全局参数'!$B$4 | C9: =IF(MOD(A9,'全局参数'!$B$6)=0,'全局参数'!$B$5,0)+'全局参数'!$B$7 | D9: =D8+B9-C9 | E9: ='全局参数'!$B$8 | F9: ='全局参数'!$B$9+'全局参数'!$B$10 | G9: =G8+E9-F9 | H9: H8+('全局参数'!$B$11-'全局参数'!$B$12) | I9: I8+('全局参数'!$B$13-'全局参数'!$B$14)
A10: 7 | B10: ='全局参数'!$B$4 | C10: =IF(MOD(A10,'全局参数'!$B$6)=0,'全局参数'!$B$5,0)+'全局参数'!$B$7 | D10: =D9+B10-C10 | E10: ='全局参数'!$B$8 | F10: ='全局参数'!$B$9+'全局参数'!$B$10 | G10: =G9+E10-F10 | H10: H9+('全局参数'!$B$11-'全局参数'!$B$12) | I10: I9+('全局参数'!$B$13-'全局参数'!$B$14)
A11: 8 | B11: ='全局参数'!$B$4 | C11: =IF(MOD(A11,'全局参数'!$B$6)=0,'全局参数'!$B$5,0)+'全局参数'!$B$7 | D11: =D10+B11-C11 | E11: ='全局参数'!$B$8 | F11: ='全局参数'!$B$9+'全局参数'!$B$10 | G11: =G10+E11-F11 | H11: H10+('全局参数'!$B$11-'全局参数'!$B$12) | I11: I10+('全局参数'!$B$13-'全局参数'!$B$14)
A12: 9 | B12: ='全局参数'!$B$4 | C12: =IF(MOD(A12,'全局参数'!$B$6)=0,'全局参数'!$B$5,0)+'全局参数'!$B$7 | D12: =D11+B12-C12 | E12: ='全局参数'!$B$8 | F12: ='全局参数'!$B$9+'全局参数'!$B$10 | G12: =G11+E12-F12 | H12: H11+('全局参数'!$B$11-'全局参数'!$B$12) | I12: I11+('全局参数'!$B$13-'全局参数'!$B$14)
A13: 10 | B13: ='全局参数'!$B$4 | C13: =IF(MOD(A13,'全局参数'!$B$6)=0,'全局参数'!$B$5,0)+'全局参数'!$B$7 | D13: =D12+B13-C13 | E13: ='全局参数'!$B$8 | F13: ='全局参数'!$B$9+'全局参数'!$B$10 | G13: =G12+E13-F13 | H13: H12+('全局参数'!$B$11-'全局参数'!$B$12) | I13: I12+('全局参数'!$B$13-'全局参数'!$B$14)
A14: 11 | B14: ='全局参数'!$B$4 | C14: =IF(MOD(A14,'全局参数'!$B$6)=0,'全局参数'!$B$5,0)+'全局参数'!$B$7 | D14: =D13+B14-C14 | E14: ='全局参数'!$B$8 | F14: ='全局参数'!$B$9+'全局参数'!$B$10 | G14: =G13+E14-F14 | H14: H13+('全局参数'!$B$11-'全局参数'!$B$12) | I14: I13+('全局参数'!$B$13-'全局参数'!$B$14)
A15: 12 | B15: ='全局参数'!$B$4 | C15: =IF(MOD(A15,'全局参数'!$B$6)=0,'全局参数'!$B$5,0)+'全局参数'!$B$7 | D15: =D14+B15-C15 | E15: ='全局参数'!$B$8 | F15: ='全局参数'!$B$9+'全局参数'!$B$10 | G15: =G14+E15-F15 | H15: H14+('全局参数'!$B$11-'全局参数'!$B$12) | I15: I14+('全局参数'!$B$13-'全局参数'!$B$14)
A16: 13 | B16: ='全局参数'!$B$4 | C16: =IF(MOD(A16,'全局参数'!$B$6)=0,'全局参数'!$B$5,0)+'全局参数'!$B$7 | D16: =D15+B16-C16 | E16: ='全局参数'!$B$8 | F16: ='全局参数'!$B$9+'全局参数'!$B$10 | G16: =G15+E16-F16 | H16: H15+('全局参数'!$B$11-'全局参数'!$B$12) | I16: I15+('全局参数'!$B$13-'全局参数'!$B$14)
... A93: 90 | B93: ='全局参数'!$B$4 | C93: =IF(MOD(A93,'全局参数'!$B$6)=0,'全局参数'!$B$5,0)+'全局参数'!$B$7 | D93: =D92+B93-C93 | E93: ='全局参数'!$B$8 | F93: ='全局参数'!$B$9+'全局参数'!$B$10 | G93: =G92+E93-F93 | H93: H92+('全局参数'!$B$11-'全局参数'!$B$12) | I93: I92+('全局参数'!$B$13-'全局参数'!$B$14)

Sheet 生态校验
A1: 90 天生态校验（产出 / 消耗 / 结余 / 运营结论）
A3: 天空石 | B3: =SUMPRODUCT(('90天收支模拟'!B4:B93)*1) | C3: =SUM('90天收支模拟'!C4:C93) | D3: ='90天收支模拟'!D93 | E3: 结论：投放克制、结余为正——硬通货紧缩是本作抽卡节奏的核心；抽卡补充依赖活动赠送招募券（不占天空石）
A4: 金币 | B4: =SUM('90天收支模拟'!E4:E93) | C4: =SUM('90天收支模拟'!F4:F93) | D4: ='90天收支模拟'!G93 | E4: 结论：净投放大幅为正（长线通胀）——必须设计回收口：装备重铸 / 限时商店 / 多英雄平行培养，否则金币在中后期失去约束力
A5: 体力 | B5: =900*90 | C5: =850*90 | D5: ='90天收支模拟'!H93 | E5: 结论：紧平衡（日均结余 50）——体力是日活闸门：玩家永远"差一点"，每日刷图选择构成隐性的资源配置决策
A6: 荣誉 | B6: =300*90 | C6: =250*90 | D6: ='90天收支模拟'!I93 | E6: 结论：微正结余——专用币允许小幅盈余，兑换商店定期上新消耗库存
A9: 方法论：经济是流量系统——逐日收支模拟比"拍一个总产出"更能暴露通胀时点与缺口。本表证明：①金币必须加回收口 ②天空石投放克制是抽卡体验的前提 ③体力紧平衡即日活闸门。

Sheet 说明
A1: 内容
A2: ① 标准玩家画像：零充/轻付费，收支模型以全局参数为唯一参数源
A3: ② 90 天模拟：余额公式逐日累计，天空石含周期性十连支出（每 30 天一次）
A4: ③ 生态校验：四种货币四种结论——天空石紧缩 / 金币通胀需回收 / 体力紧平衡 / 专用币微正
A5: ④ 图表：天空石余额与金币余额曲线，直观展示抽卡节奏与通胀走势
